{"fixtures":[],"history":[{"own_goals":0,"transfers_in":104377,"round":6,"expected_goals_conceded":"0.81","bonus":0,"clean_sheets":0,"goals_conceded":0,"penalties_saved":0,"opponent_team":1,"threat":"25.0","bps":18,"influence":"38.4","goals_scored":1,"transfers_balance":93207,"ict_index":"6.5","fixture":56,"team_h_score":3,"starts":1,"kickoff_time":"2022-09-04T15:30:00Z","was_home":true,"yellow_cards":0,"expected_assists":"0.01","element":609,"selected":106719,"minutes":57,"expected_goal_involvements":"0.42","saves":0,"value":75,"transfers_out":11170,"penalties_missed":0,"team_a_score":1,"expected_goals":"0.41","creativity":"1.6","assists":0,"red_cards":0,"total_points":6},{"own_goals":0,"transfers_in":70841,"round":9,"expected_goals_conceded":"3.30","bonus":0,"clean_sheets":0,"goals_conceded":6,"penalties_saved":0,"opponent_team":13,"threat":"53.0","bps":27,"influence":"42.2","goals_scored":1,"transfers_balance":22342,"ict_index":"10.9","fixture":88,"team_h_score":6,"starts":1,"kickoff_time":"2022-10-02T13:00:00Z","was_home":false,"yellow_cards":0,"expected_assists":"0.06","element":609,"selected":530066,"minutes":90,"expected_goal_involvements":"0.30","saves":0,"value":75,"transfers_out":48499,"penalties_missed":0,"team_a_score":3,"expected_goals":"0.24","creativity":"14.1","assists":0,"red_cards":0,"total_points":7},{"own_goals":0,"transfers_in":173998,"round":10,"expected_goals_conceded":"0.54","bonus":1,"clean_sheets":0,"goals_conceded":1,"penalties_saved":0,"opponent_team":8,"threat":"33.0","bps":28,"influence":"44.6","goals_scored":1,"transfers_balance":133132,"ict_index":"11.3","fixture":96,"team_h_score":1,"starts":1,"kickoff_time":"2022-10-09T18:00:00Z","was_home":false,"yellow_cards":0,"expected_assists":"0.09","element":609,"selected":681685,"minutes":90,"expected_goal_involvements":"0.50","saves":0,"value":75,"transfers_out":40866,"penalties_missed":0,"team_a_score":2,"expected_goals":"0.41","creativity":"35.5","assists":0,"red_cards":0,"total_points":8},{"own_goals":0,"transfers_in":303376,"round":11,"expected_goals_conceded":"0.91","bonus":0,"clean_sheets":1,"goals_conceded":0,"penalties_saved":0,"opponent_team":15,"threat":"49.0","bps":12,"influence":"8.0","goals_scored":0,"transfers_balance":277228,"ict_index":"6.6","fixture":107,"team_h_score":0,"starts":1,"kickoff_time":"2022-10-16T13:00:00Z","was_home":true,"yellow_cards":0,"expected_assists":"0.03","element":609,"selected":975801,"minutes":90,"expected_goal_involvements":"0.19","saves":0,"value":76,"transfers_out":26148,"penalties_missed":0,"team_a_score":0,"expected_goals":"0.16","creativity":"9.0","assists":0,"red_cards":0,"total_points":3},{"own_goals":0,"transfers_in":121708,"round":12,"expected_goals_conceded":"0.58","bonus":0,"clean_sheets":1,"goals_conceded":0,"penalties_saved":0,"opponent_team":18,"threat":"32.0","bps":8,"influence":"3.2","goals_scored":0,"transfers_balance":78949,"ict_index":"4.3","fixture":119,"team_h_score":2,"starts":1,"kickoff_time":"2022-10-19T19:15:00Z","was_home":true,"yellow_cards":0,"expected_assists":"0.10","element":609,"selected":1114041,"minutes":75,"expected_goal_involvements":"0.29","saves":0,"value":76,"transfers_out":42759,"penalties_missed":0,"team_a_score":0,"expected_goals":"0.19","creativity":"7.8","assists":0,"red_cards":0,"total_points":3},{"own_goals":0,"transfers_in":77909,"round":13,"expected_goals_conceded":"1.06","bonus":0,"clean_sheets":0,"goals_conceded":1,"penalties_saved":0,"opponent_team":6,"threat":"15.0","bps":9,"influence":"10.6","goals_scored":0,"transfers_balance":-646,"ict_index":"6.6","fixture":122,"team_h_score":1,"starts":1,"kickoff_time":"2022-10-22T16:30:00Z","was_home":false,"yellow_cards":1,"expected_assists":"0.18","element":609,"selected":1053378,"minutes":90,"expected_goal_involvements":"0.43","saves":0,"value":76,"transfers_out":78555,"penalties_missed":0,"team_a_score":1,"expected_goals":"0.25","creativity":"39.9","assists":0,"red_cards":0,"total_points":1},{"own_goals":0,"transfers_in":100706,"round":14,"expected_goals_conceded":"0.00","bonus":0,"clean_sheets":0,"goals_conceded":0,"penalties_saved":0,"opponent_team":19,"threat":"0.0","bps":0,"influence":"0.0","goals_scored":0,"transfers_balance":-4590,"ict_index":"0.0","fixture":139,"team_h_score":1,"starts":0,"kickoff_time":"2022-10-30T16:15:00Z","was_home":true,"yellow_cards":0,"expected_assists":"0.00","element":609,"selected":1057097,"minutes":0,"expected_goal_involvements":"0.00","saves":0,"value":76,"transfers_out":105296,"penalties_missed":0,"team_a_score":0,"expected_goals":"0.00","creativity":"0.0","assists":0,"red_cards":0,"total_points":0},{"own_goals":0,"transfers_in":17767,"round":15,"expected_goals_conceded":"0.00","bonus":0,"clean_sheets":0,"goals_conceded":0,"penalties_saved":0,"opponent_team":2,"threat":"0.0","bps":0,"influence":"0.0","goals_scored":0,"transfers_balance":-330350,"ict_index":"0.0","fixture":141,"team_h_score":3,"starts":0,"kickoff_time":"2022-11-06T14:00:00Z","was_home":false,"yellow_cards":0,"expected_assists":"0.00","element":609,"selected":722161,"minutes":0,"expected_goal_involvements":"0.00","saves":0,"value":76,"transfers_out":348117,"penalties_missed":0,"team_a_score":1,"expected_goals":"0.00","creativity":"0.0","assists":0,"red_cards":0,"total_points":0},{"own_goals":0,"transfers_in":1860,"round":16,"expected_goals_conceded":"0.00","bonus":0,"clean_sheets":0,"goals_conceded":0,"penalties_saved":0,"opponent_team":9,"threat":"0.0","bps":0,"influence":"0.0","goals_scored":0,"transfers_balance":-193810,"ict_index":"0.0","fixture":153,"team_h_score":1,"starts":0,"kickoff_time":"2022-11-13T16:30:00Z","was_home":false,"yellow_cards":0,"expected_assists":"0.00","element":609,"selected":535311,"minutes":0,"expected_goal_involvements":"0.00","saves":0,"value":75,"transfers_out":195670,"penalties_missed":0,"team_a_score":2,"expected_goals":"0.00","creativity":"0.0","assists":0,"red_cards":0,"total_points":0},{"own_goals":0,"transfers_in":55675,"round":17,"expected_goals_conceded":"0.20","bonus":0,"clean_sheets":1,"goals_conceded":0,"penalties_saved":0,"opponent_team":16,"threat":"20.0","bps":1,"influence":"0.0","goals_scored":0,"transfers_balance":-69634,"ict_index":"2.4","fixture":169,"team_h_score":3,"starts":1,"kickoff_time":"2022-12-27T20:00:00Z","was_home":true,"yellow_cards":0,"expected_assists":"0.03","element":609,"selected":473027,"minutes":64,"expected_goal_involvements":"0.51","saves":0,"value":75,"transfers_out":125309,"penalties_missed":0,"team_a_score":0,"expected_goals":"0.48","creativity":"4.4","assists":0,"red_cards":0,"total_points":3},{"own_goals":0,"transfers_in":7881,"round":18,"expected_goals_conceded":"0.54","bonus":0,"clean_sheets":1,"goals_conceded":0,"penalties_saved":0,"opponent_team":20,"threat":"88.0","bps":5,"influence":"11.6","goals_scored":0,"transfers_balance":-29265,"ict_index":"10.6","fixture":180,"team_h_score":0,"starts":1,"kickoff_time":"2022-12-31T12:30:00Z","was_home":false,"yellow_cards":0,"expected_assists":"0.02","element":609,"selected":445647,"minutes":90,"expected_goal_involvements":"0.40","saves":0,"value":75,"transfers_out":37146,"penalties_missed":0,"team_a_score":1,"expected_goals":"0.38","creativity":"6.6","assists":0,"red_cards":0,"total_points":3},{"own_goals":0,"transfers_in":6378,"round":19,"expected_goals_conceded":"0.00","bonus":0,"clean_sheets":0,"goals_conceded":0,"penalties_saved":0,"opponent_team":3,"threat":"0.0","bps":0,"influence":"0.0","goals_scored":0,"transfers_balance":-23229,"ict_index":"0.0","fixture":189,"team_h_score":3,"starts":0,"kickoff_time":"2023-01-03T20:00:00Z","was_home":true,"yellow_cards":0,"expected_assists":"0.00","element":609,"selected":423479,"minutes":0,"expected_goal_involvements":"0.00","saves":0,"value":74,"transfers_out":29607,"penalties_missed":0,"team_a_score":0,"expected_goals":"0.00","creativity":"0.0","assists":0,"red_cards":0,"total_points":0},{"own_goals":0,"transfers_in":31542,"round":20,"expected_goals_conceded":"0.52","bonus":0,"clean_sheets":0,"goals_conceded":1,"penalties_saved":0,"opponent_team":13,"threat":"0.0","bps":2,"influence":"2.2","goals_scored":0,"transfers_balance":-16142,"ict_index":"0.3","fixture":196,"team_h_score":2,"starts":0,"kickoff_time":"2023-01-14T12:30:00Z","was_home":true,"yellow_cards":0,"expected_assists":"0.04","element":609,"selected":411504,"minutes":45,"expected_goal_involvements":"0.04","saves":0,"value":74,"transfers_out":47684,"penalties_missed":0,"team_a_score":1,"expected_goals":"0.00","creativity":"0.5","assists":0,"red_cards":0,"total_points":1},{"own_goals":0,"transfers_in":31542,"round":20,"expected_goals_conceded":"0.33","bonus":0,"clean_sheets":1,"goals_conceded":0,"penalties_saved":0,"opponent_team":7,"threat":"14.0","bps":7,"influence":"2.0","goals_scored":0,"transfers_balance":-16142,"ict_index":"2.0","fixture":63,"team_h_score":1,"starts":1,"kickoff_time":"2023-01-18T20:00:00Z","was_home":false,"yellow_cards":0,"expected_assists":"0.07","element":609,"selected":411504,"minutes":69,"expected_goal_involvements":"0.24","saves":0,"value":74,"transfers_out":47684,"penalties_missed":0,"team_a_score":1,"expected_goals":"0.17","creativity":"4.4","assists":0,"red_cards":0,"total_points":3},{"own_goals":0,"transfers_in":5711,"round":21,"expected_goals_conceded":"1.63","bonus":0,"clean_sheets":0,"goals_conceded":2,"penalties_saved":0,"opponent_team":1,"threat":"4.0","bps":5,"influence":"6.6","goals_scored":0,"transfers_balance":-28475,"ict_index":"2.3","fixture":201,"team_h_score":3,"starts":1,"kickoff_time":"2023-01-22T16:30:00Z","was_home":false,"yellow_cards":1,"expected_assists":"0.02","element":609,"selected":382269,"minutes":70,"expected_goal_involvements":"0.04","saves":0,"value":74,"transfers_out":34186,"penalties_missed":0,"team_a_score":2,"expected_goals":"0.02","creativity":"12.8","assists":0,"red_cards":0,"total_points":1},{"own_goals":0,"transfers_in":23486,"round":22,"expected_goals_conceded":"1.17","bonus":0,"clean_sheets":0,"goals_conceded":1,"penalties_saved":0,"opponent_team":7,"threat":"11.0","bps":8,"influence":"5.8","goals_scored":0,"transfers_balance":-8344,"ict_index":"2.4","fixture":216,"team_h_score":2,"starts":1,"kickoff_time":"2023-02-04T15:00:00Z","was_home":true,"yellow_cards":1,"expected_assists":"0.05","element":609,"selected":376062,"minutes":80,"expected_goal_involvements":"0.12","saves":0,"value":73,"transfers_out":31830,"penalties_missed":0,"team_a_score":1,"expected_goals":"0.07","creativity":"7.4","assists":0,"red_cards":0,"total_points":1},{"own_goals":0,"transfers_in":23486,"round":22,"expected_goals_conceded":"0.00","bonus":0,"clean_sheets":0,"goals_conceded":0,"penalties_saved":0,"opponent_team":11,"threat":"0.0","bps":0,"influence":"0.0","goals_scored":0,"transfers_balance":-8344,"ict_index":"0.0","fixture":76,"team_h_score":2,"starts":0,"kickoff_time":"2023-02-08T20:00:00Z","was_home":true,"yellow_cards":0,"expected_assists":"0.00","element":609,"selected":376062,"minutes":0,"expected_goal_involvements":"0.00","saves":0,"value":73,"transfers_out":31830,"penalties_missed":0,"team_a_score":2,"expected_goals":"0.00","creativity":"0.0","assists":0,"red_cards":0,"total_points":0},{"own_goals":0,"transfers_in":1807,"round":23,"expected_goals_conceded":"0.00","bonus":0,"clean_sheets":0,"goals_conceded":0,"penalties_saved":0,"opponent_team":11,"threat":"0.0","bps":0,"influence":"0.0","goals_scored":0,"transfers_balance":-37017,"ict_index":"0.0","fixture":225,"team_h_score":0,"starts":0,"kickoff_time":"2023-02-12T14:00:00Z","was_home":false,"yellow_cards":0,"expected_assists":"0.00","element":609,"selected":339313,"minutes":0,"expected_goal_involvements":"0.00","saves":0,"value":73,"transfers_out":38824,"penalties_missed":0,"team_a_score":2,"expected_goals":"0.00","creativity":"0.0","assists":0,"red_cards":0,"total_points":0},{"own_goals":0,"transfers_in":147,"round":24,"expected_goals_conceded":"0.00","bonus":0,"clean_sheets":0,"goals_conceded":0,"penalties_saved":0,"opponent_team":10,"threat":"0.0","bps":0,"influence":"0.0","goals_scored":0,"transfers_balance":-22012,"ict_index":"0.0","fixture":236,"team_h_score":3,"starts":0,"kickoff_time":"2023-02-19T14:00:00Z","was_home":true,"yellow_cards":0,"expected_assists":"0.00","element":609,"selected":317809,"minutes":0,"expected_goal_involvements":"0.00","saves":0,"value":73,"transfers_out":22159,"penalties_missed":0,"team_a_score":0,"expected_goals":"0.00","creativity":"0.0","assists":0,"red_cards":0,"total_points":0},{"own_goals":0,"transfers_in":5021,"round":26,"expected_goals_conceded":"2.65","bonus":0,"clean_sheets":0,"goals_conceded":7,"penalties_saved":0,"opponent_team":12,"threat":"20.0","bps":-2,"influence":"6.8","goals_scored":0,"transfers_balance":1295,"ict_index":"3.9","fixture":256,"team_h_score":7,"starts":1,"kickoff_time":"2023-03-05T16:30:00Z","was_home":false,"yellow_cards":1,"expected_assists":"0.01","element":609,"selected":309224,"minutes":90,"expected_goal_involvements":"0.07","saves":0,"value":73,"transfers_out":3726,"penalties_missed":0,"team_a_score":0,"expected_goals":"0.06","creativity":"12.2","assists":0,"red_cards":0,"total_points":1},{"own_goals":0,"transfers_in":3931,"round":27,"expected_goals_conceded":"1.11","bonus":0,"clean_sheets":1,"goals_conceded":0,"penalties_saved":0,"opponent_team":17,"threat":"4.0","bps":9,"influence":"7.0","goals_scored":0,"transfers_balance":-966,"ict_index":"3.3","fixture":267,"team_h_score":0,"starts":1,"kickoff_time":"2023-03-12T14:00:00Z","was_home":true,"yellow_cards":0,"expected_assists":"0.07","element":609,"selected":309107,"minutes":73,"expected_goal_involvements":"0.10","saves":0,"value":73,"transfers_out":4897,"penalties_missed":0,"team_a_score":0,"expected_goals":"0.03","creativity":"22.0","assists":0,"red_cards":0,"total_points":3},{"own_goals":0,"transfers_in":12804,"round":29,"expected_goals_conceded":"1.81","bonus":0,"clean_sheets":1,"goals_conceded":0,"penalties_saved":0,"opponent_team":15,"threat":"13.0","bps":8,"influence":"8.0","goals_scored":0,"transfers_balance":9617,"ict_index":"3.3","fixture":288,"team_h_score":2,"starts":1,"kickoff_time":"2023-04-02T15:30:00Z","was_home":false,"yellow_cards":0,"expected_assists":"0.05","element":609,"selected":318942,"minutes":61,"expected_goal_involvements":"0.15","saves":0,"value":73,"transfers_out":3187,"penalties_missed":0,"team_a_score":0,"expected_goals":"0.10","creativity":"12.2","assists":0,"red_cards":0,"total_points":3},{"own_goals":0,"transfers_in":12804,"round":29,"expected_goals_conceded":"0.55","bonus":0,"clean_sheets":1,"goals_conceded":0,"penalties_saved":0,"opponent_team":4,"threat":"17.0","bps":4,"influence":"0.0","goals_scored":0,"transfers_balance":9617,"ict_index":"3.6","fixture":247,"team_h_score":1,"starts":1,"kickoff_time":"2023-04-05T19:00:00Z","was_home":true,"yellow_cards":0,"expected_assists":"0.34","element":609,"selected":318942,"minutes":85,"expected_goal_involvements":"0.62","saves":0,"value":73,"transfers_out":3187,"penalties_missed":0,"team_a_score":0,"expected_goals":"0.28","creativity":"21.8","assists":0,"red_cards":0,"total_points":3},{"own_goals":0,"transfers_in":4509,"round":30,"expected_goals_conceded":"0.64","bonus":0,"clean_sheets":0,"goals_conceded":0,"penalties_saved":0,"opponent_team":8,"threat":"45.0","bps":7,"influence":"14.6","goals_scored":0,"transfers_balance":-858,"ict_index":"9.0","fixture":297,"team_h_score":2,"starts":1,"kickoff_time":"2023-04-08T11:30:00Z","was_home":true,"yellow_cards":0,"expected_assists":"0.14","element":609,"selected":318018,"minutes":59,"expected_goal_involvements":"0.62","saves":0,"value":73,"transfers_out":5367,"penalties_missed":0,"team_a_score":0,"expected_goals":"0.48","creativity":"30.8","assists":0,"red_cards":0,"total_points":1},{"own_goals":0,"transfers_in":18348,"round":31,"expected_goals_conceded":"0.68","bonus":3,"clean_sheets":1,"goals_conceded":0,"penalties_saved":0,"opponent_team":16,"threat":"56.0","bps":38,"influence":"47.2","goals_scored":1,"transfers_balance":12667,"ict_index":"12.7","fixture":306,"team_h_score":0,"starts":1,"kickoff_time":"2023-04-16T15:30:00Z","was_home":false,"yellow_cards":0,"expected_assists":"0.39","element":609,"selected":331704,"minutes":90,"expected_goal_involvements":"1.51","saves":0,"value":73,"transfers_out":5681,"penalties_missed":0,"team_a_score":2,"expected_goals":"1.12","creativity":"24.1","assists":1,"red_cards":0,"total_points":14},{"own_goals":0,"transfers_in":10971,"round":33,"expected_goals_conceded":"1.54","bonus":0,"clean_sheets":0,"goals_conceded":1,"penalties_saved":0,"opponent_team":18,"threat":"13.0","bps":15,"influence":"13.4","goals_scored":0,"transfers_balance":5730,"ict_index":"5.1","fixture":325,"team_h_score":2,"starts":1,"kickoff_time":"2023-04-27T19:15:00Z","was_home":false,"yellow_cards":0,"expected_assists":"0.12","element":609,"selected":343571,"minutes":70,"expected_goal_involvements":"0.14","saves":0,"value":73,"transfers_out":5241,"penalties_missed":0,"team_a_score":2,"expected_goals":"0.02","creativity":"24.2","assists":0,"red_cards":0,"total_points":2},{"own_goals":0,"transfers_in":14443,"round":34,"expected_goals_conceded":"0.26","bonus":0,"clean_sheets":0,"goals_conceded":0,"penalties_saved":0,"opponent_team":2,"threat":"19.0","bps":2,"influence":"2.2","goals_scored":0,"transfers_balance":5572,"ict_index":"2.2","fixture":339,"team_h_score":1,"starts":0,"kickoff_time":"2023-04-30T13:00:00Z","was_home":true,"yellow_cards":0,"expected_assists":"0.02","element":609,"selected":351593,"minutes":14,"expected_goal_involvements":"0.12","saves":0,"value":73,"transfers_out":8871,"penalties_missed":0,"team_a_score":0,"expected_goals":"0.10","creativity":"0.6","assists":0,"red_cards":0,"total_points":1},{"own_goals":0,"transfers_in":14443,"round":34,"expected_goals_conceded":"1.16","bonus":0,"clean_sheets":1,"goals_conceded":0,"penalties_saved":0,"opponent_team":5,"threat":"19.0","bps":-2,"influence":"5.2","goals_scored":0,"transfers_balance":5572,"ict_index":"5.7","fixture":274,"team_h_score":1,"starts":1,"kickoff_time":"2023-05-04T19:00:00Z","was_home":false,"yellow_cards":1,"expected_assists":"0.10","element":609,"selected":351593,"minutes":75,"expected_goal_involvements":"0.59","saves":0,"value":73,"transfers_out":8871,"penalties_missed":0,"team_a_score":0,"expected_goals":"0.49","creativity":"32.3","assists":0,"red_cards":0,"total_points":2},{"own_goals":0,"transfers_in":2419,"round":35,"expected_goals_conceded":"1.29","bonus":0,"clean_sheets":0,"goals_conceded":1,"penalties_saved":0,"opponent_team":19,"threat":"18.0","bps":17,"influence":"13.6","goals_scored":0,"transfers_balance":-10738,"ict_index":"7.3","fixture":349,"team_h_score":1,"starts":1,"kickoff_time":"2023-05-07T18:00:00Z","was_home":false,"yellow_cards":0,"expected_assists":"0.09","element":609,"selected":339532,"minutes":73,"expected_goal_involvements":"0.30","saves":0,"value":73,"transfers_out":13157,"penalties_missed":0,"team_a_score":0,"expected_goals":"0.21","creativity":"41.2","assists":0,"red_cards":0,"total_points":2},{"own_goals":0,"transfers_in":12719,"round":36,"expected_goals_conceded":"0.39","bonus":0,"clean_sheets":1,"goals_conceded":0,"penalties_saved":0,"opponent_team":20,"threat":"49.0","bps":23,"influence":"25.6","goals_scored":0,"transfers_balance":4723,"ict_index":"11.1","fixture":359,"team_h_score":2,"starts":1,"kickoff_time":"2023-05-13T14:00:00Z","was_home":true,"yellow_cards":0,"expected_assists":"0.23","element":609,"selected":344996,"minutes":90,"expected_goal_involvements":"0.98","saves":0,"value":73,"transfers_out":7996,"penalties_missed":0,"team_a_score":0,"expected_goals":"0.75","creativity":"36.1","assists":1,"red_cards":0,"total_points":6},{"own_goals":0,"transfers_in":149373,"round":37,"expected_goals_conceded":"1.16","bonus":0,"clean_sheets":1,"goals_conceded":0,"penalties_saved":0,"opponent_team":3,"threat":"15.0","bps":12,"influence":"3.2","goals_scored":0,"transfers_balance":142799,"ict_index":"3.7","fixture":361,"team_h_score":0,"starts":1,"kickoff_time":"2023-05-20T14:00:00Z","was_home":false,"yellow_cards":0,"expected_assists":"0.09","element":609,"selected":498319,"minutes":85,"expected_goal_involvements":"0.30","saves":0,"value":73,"transfers_out":6574,"penalties_missed":0,"team_a_score":1,"expected_goals":"0.21","creativity":"18.7","assists":0,"red_cards":0,"total_points":3},{"own_goals":0,"transfers_in":149373,"round":37,"expected_goals_conceded":"0.54","bonus":0,"clean_sheets":0,"goals_conceded":0,"penalties_saved":0,"opponent_team":6,"threat":"1.0","bps":1,"influence":"0.0","goals_scored":0,"transfers_balance":142799,"ict_index":"0.0","fixture":319,"team_h_score":4,"starts":1,"kickoff_time":"2023-05-25T19:00:00Z","was_home":true,"yellow_cards":0,"expected_assists":"0.07","element":609,"selected":498319,"minutes":28,"expected_goal_involvements":"0.09","saves":0,"value":73,"transfers_out":6574,"penalties_missed":0,"team_a_score":1,"expected_goals":"0.02","creativity":"0.8","assists":0,"red_cards":0,"total_points":1},{"own_goals":0,"transfers_in":4345,"round":38,"expected_goals_conceded":"0.00","bonus":0,"clean_sheets":0,"goals_conceded":0,"penalties_saved":0,"opponent_team":9,"threat":"0.0","bps":0,"influence":"0.0","goals_scored":0,"transfers_balance":-104698,"ict_index":"0.0","fixture":379,"team_h_score":2,"starts":0,"kickoff_time":"2023-05-28T15:30:00Z","was_home":true,"yellow_cards":0,"expected_assists":"0.00","element":609,"selected":379796,"minutes":0,"expected_goal_involvements":"0.00","saves":0,"value":73,"transfers_out":109043,"penalties_missed":0,"team_a_score":1,"expected_goals":"0.00","creativity":"0.0","assists":0,"red_cards":0,"total_points":0}],"history_past":[]}